genice_matcher-0.2.1.data/headers/bst.h
genice_matcher-0.2.1.data/headers/common.h
genice_matcher-0.2.1.data/headers/matcher2.h
genice_matcher-0.2.1.data/headers/neighborlist.h
genice_matcher-0.2.1.data/headers/pairlist.h
genice_matcher-0.2.1.data/headers/smatcher.h
genice_matcher-0.2.1.data/headers/svd.h
genice_matcher-0.2.1.dist-info/DESCRIPTION.rst
genice_matcher-0.2.1.dist-info/METADATA
genice_matcher-0.2.1.dist-info/RECORD
genice_matcher-0.2.1.dist-info/WHEEL
genice_matcher-0.2.1.dist-info/entry_points.txt
genice_matcher-0.2.1.dist-info/metadata.json
genice_matcher-0.2.1.dist-info/top_level.txt
matcher/__init__.py
matcher/cmatcher2.cpython-36m-darwin.so
matcher/csmatcher.cpython-36m-darwin.so
matcher/matcher2.py
matcher/matcher2yap.py
matcher/rectify.py
matcher/smatcher-average.py
matcher/smatcher-average2.py
matcher/smatcher.py
matcher/smatcher2yap.py
matcher/test_regularize.py
matcher/test_symmop.py
